findly/proto/.gitignore
findly/proto/__init__.py
findly/proto/user_action_log_pb2.py
findly/proto/user_action_log_pb2.pyi
findly_proto-0.1.1.dist-info/METADATA
findly_proto-0.1.1.dist-info/WHEEL
findly_proto-0.1.1.dist-info/RECORD
