Metadata-Version: 2.1
Name: findly-proto
Version: 0.1.1
Summary: 
License: GPL-3.0-only
Requires-Python: >=3.9,<4.0
Classifier: License :: OSI Approved :: GNU General Public License v3 (GPLv3)
Classifier: Programming Language :: Python :: 3
Classifier: Programming Language :: Python :: 3.9
Classifier: Programming Language :: Python :: 3.10
Classifier: Programming Language :: Python :: 3.11
Requires-Dist: protobuf (>=4.25.3,<5.0.0)
